{
  "entries": {
    "tap": {
      "homebrew/cask": {
        "revision": "bf31309bd713387e01528abe564f552b7c307826"
      },
      "go-task/tap": {
        "revision": "ebcaf57fb92012f858725eea53a18043c7ed86d6"
      }
    },
    "brew": {
      "go": {
        "version": "1.16.3",
        "bottle": {
          "rebuild": 0,
          "cellar": "/usr/local/Cellar",
          "prefix": "/usr/local",
          "root_url": "https://homebrew.bintray.com/bottles",
          "files": {
            "arm64_big_sur": {
              "url": "https://homebrew.bintray.com/bottles/go-1.16.3.arm64_big_sur.bottle.tar.gz",
              "sha256": "e7c1efdd09e951eb46d01a3200b01e7fa55ce285b75470051be7fef34f4233ce"
            },
            "big_sur": {
              "url": "https://homebrew.bintray.com/bottles/go-1.16.3.big_sur.bottle.tar.gz",
              "sha256": "ea37f33fd27369612a3e4e6db6adc46db0e8bdf6fac1332bf51bafaa66d43969"
            },
            "catalina": {
              "url": "https://homebrew.bintray.com/bottles/go-1.16.3.catalina.bottle.tar.gz",
              "sha256": "69c28f5e60612801c66e51e93d32068f822b245ab83246cb6cb374572eb59e15"
            },
            "mojave": {
              "url": "https://homebrew.bintray.com/bottles/go-1.16.3.mojave.bottle.tar.gz",
              "sha256": "bf1e90ed1680b8ee1acb49f2f99426c8a8ac3e49efd63c7f3b41e57e7214dd19"
            }
          }
        }
      },
      "go-task": {
        "version": "3.3.0",
        "bottle": false
      },
      "bzip2": {
        "version": "1.0.8",
        "bottle": {
          "rebuild": 1,
          "cellar": ":any_skip_relocation",
          "prefix": "/usr/local",
          "root_url": "https://homebrew.bintray.com/bottles",
          "files": {
            "arm64_big_sur": {
              "url": "https://homebrew.bintray.com/bottles/bzip2-1.0.8.arm64_big_sur.bottle.1.tar.gz",
              "sha256": "34bcbd41ffc141ea961a31b2109637a18628768a4af1856b9ecb3f80fed587b7"
            },
            "big_sur": {
              "url": "https://homebrew.bintray.com/bottles/bzip2-1.0.8.big_sur.bottle.1.tar.gz",
              "sha256": "e3809e379c13b3af3e18e3533f54e7bdee1c630cfce6143816be859321afa020"
            },
            "catalina": {
              "url": "https://homebrew.bintray.com/bottles/bzip2-1.0.8.catalina.bottle.1.tar.gz",
              "sha256": "78421d5891328cb96cce8ff6a6c20ce5930a4a74fd1b24b05ef02cd92117c5fd"
            },
            "mojave": {
              "url": "https://homebrew.bintray.com/bottles/bzip2-1.0.8.mojave.bottle.1.tar.gz",
              "sha256": "313e48f4528c1d8042a9cd4c77bd69047dedd7eda2bd350650a902e1ff549a38"
            },
            "high_sierra": {
              "url": "https://homebrew.bintray.com/bottles/bzip2-1.0.8.high_sierra.bottle.1.tar.gz",
              "sha256": "a3eedbcb61a66d3a1286685db878e19c1de90605626d1d988705f66a5aa66673"
            }
          }
        }
      },
      "coreutils": {
        "version": "8.32",
        "bottle": {
          "rebuild": 2,
          "cellar": "/usr/local/Cellar",
          "prefix": "/usr/local",
          "root_url": "https://homebrew.bintray.com/bottles",
          "files": {
            "arm64_big_sur": {
              "url": "https://homebrew.bintray.com/bottles/coreutils-8.32.arm64_big_sur.bottle.2.tar.gz",
              "sha256": "e7d88d2b7a91a57dfd37c2ea14752d1bb116f25694eab1161d6e8088f7db5921"
            },
            "big_sur": {
              "url": "https://homebrew.bintray.com/bottles/coreutils-8.32.big_sur.bottle.2.tar.gz",
              "sha256": "371ec57703b3646e0113331308b6e03617c2a7f91e15e113380b605455daba20"
            },
            "catalina": {
              "url": "https://homebrew.bintray.com/bottles/coreutils-8.32.catalina.bottle.2.tar.gz",
              "sha256": "7a97ad96dfbe6abbb5c94424518a077e040af8a77d1946ca960a5f33cd237551"
            },
            "mojave": {
              "url": "https://homebrew.bintray.com/bottles/coreutils-8.32.mojave.bottle.2.tar.gz",
              "sha256": "10fbad2e35846c7e835cb979b5beb9edf07f3a9742ddcc3c28d9abd5fe9ccb1b"
            }
          }
        }
      },
      "helm": {
        "version": "3.5.3",
        "bottle": {
          "rebuild": 0,
          "cellar": ":any_skip_relocation",
          "prefix": "/usr/local",
          "root_url": "https://homebrew.bintray.com/bottles",
          "files": {
            "arm64_big_sur": {
              "url": "https://homebrew.bintray.com/bottles/helm-3.5.3.arm64_big_sur.bottle.tar.gz",
              "sha256": "74f08b7e0da6b0ec03769217c274dd5aa5efe7cfcfdcc19dfba77b90634d0fde"
            },
            "big_sur": {
              "url": "https://homebrew.bintray.com/bottles/helm-3.5.3.big_sur.bottle.tar.gz",
              "sha256": "69ed70c1f6153c5f0e812ca74b48bb9a07d72d979ae7e65a0b8f8f98ae341708"
            },
            "catalina": {
              "url": "https://homebrew.bintray.com/bottles/helm-3.5.3.catalina.bottle.tar.gz",
              "sha256": "9f61af6cb13b36437172ee7fb014d947c648d6fcc5bbf438a6393a23a757d64d"
            },
            "mojave": {
              "url": "https://homebrew.bintray.com/bottles/helm-3.5.3.mojave.bottle.tar.gz",
              "sha256": "cbf6b54599ce1575e7661170ffb5bc6385ad0a4c23d9efe466fda75f16be4883"
            }
          }
        }
      },
      "jq": {
        "version": "1.6",
        "bottle": {
          "rebuild": 1,
          "cellar": ":any",
          "prefix": "/usr/local",
          "root_url": "https://homebrew.bintray.com/bottles",
          "files": {
            "arm64_big_sur": {
              "url": "https://homebrew.bintray.com/bottles/jq-1.6.arm64_big_sur.bottle.1.tar.gz",
              "sha256": "674b3ae41c399f1e8e44c271b0e6909babff9fcd2e04a2127d25e2407ea4dd33"
            },
            "big_sur": {
              "url": "https://homebrew.bintray.com/bottles/jq-1.6.big_sur.bottle.1.tar.gz",
              "sha256": "bf0f8577632af7b878b6425476f5b1ab9c3bf66d65affb0c455048a173a0b6bf"
            },
            "catalina": {
              "url": "https://homebrew.bintray.com/bottles/jq-1.6.catalina.bottle.1.tar.gz",
              "sha256": "820a3c85fcbb63088b160c7edf125d7e55fc2c5c1d51569304499c9cc4b89ce8"
            },
            "mojave": {
              "url": "https://homebrew.bintray.com/bottles/jq-1.6.mojave.bottle.1.tar.gz",
              "sha256": "71f0e76c5b22e5088426c971d5e795fe67abee7af6c2c4ae0cf4c0eb98ed21ff"
            },
            "high_sierra": {
              "url": "https://homebrew.bintray.com/bottles/jq-1.6.high_sierra.bottle.1.tar.gz",
              "sha256": "dffcffa4ea13e8f0f2b45c5121e529077e135ae9a47254c32182231662ee9b72"
            },
            "sierra": {
              "url": "https://homebrew.bintray.com/bottles/jq-1.6.sierra.bottle.1.tar.gz",
              "sha256": "bb4d19dc026c2d72c53eed78eaa0ab982e9fcad2cd2acc6d13e7a12ff658e877"
            }
          }
        }
      },
      "curl": {
        "version": "7.76.0",
        "bottle": {
          "rebuild": 0,
          "cellar": ":any",
          "prefix": "/usr/local",
          "root_url": "https://homebrew.bintray.com/bottles",
          "files": {
            "arm64_big_sur": {
              "url": "https://homebrew.bintray.com/bottles/curl-7.76.0.arm64_big_sur.bottle.tar.gz",
              "sha256": "c75e1385f0523744417f8072bd2f0f599af44fc311b3a08fb1033be0f1c5211c"
            },
            "big_sur": {
              "url": "https://homebrew.bintray.com/bottles/curl-7.76.0.big_sur.bottle.tar.gz",
              "sha256": "75d8508af0a6f1751b945b275b2cd11442ce3deaab7705d133df78e49f54c9d7"
            },
            "catalina": {
              "url": "https://homebrew.bintray.com/bottles/curl-7.76.0.catalina.bottle.tar.gz",
              "sha256": "8fdce9efca666c19d3a39d344fd19be778ef54c7f95e6aceff983d3cf8b908ca"
            },
            "mojave": {
              "url": "https://homebrew.bintray.com/bottles/curl-7.76.0.mojave.bottle.tar.gz",
              "sha256": "6cdf493afffb313888edb9fc4455e635e0b3a692cd19931f330cfa5457e1c1c9"
            }
          }
        }
      },
      "git": {
        "version": "2.31.1",
        "bottle": {
          "rebuild": 0,
          "cellar": "/usr/local/Cellar",
          "prefix": "/usr/local",
          "root_url": "https://homebrew.bintray.com/bottles",
          "files": {
            "arm64_big_sur": {
              "url": "https://homebrew.bintray.com/bottles/git-2.31.1.arm64_big_sur.bottle.tar.gz",
              "sha256": "82be780c2468d4e315f861ea797e98a93084bb754d8610c06a346eea74d82150"
            },
            "big_sur": {
              "url": "https://homebrew.bintray.com/bottles/git-2.31.1.big_sur.bottle.tar.gz",
              "sha256": "cf1fe81d5928efa530d891ec341d34c262b1eb7ea457191359476168ae323b93"
            },
            "catalina": {
              "url": "https://homebrew.bintray.com/bottles/git-2.31.1.catalina.bottle.tar.gz",
              "sha256": "6247bd388d85b30900923c32c0cd10caf7d48d41429c8f65a780d61b493ee9a4"
            },
            "mojave": {
              "url": "https://homebrew.bintray.com/bottles/git-2.31.1.mojave.bottle.tar.gz",
              "sha256": "ff281db6c9d895705c252ab4a7798c7274df2484c8cd5f22647e76c83ceabfca"
            }
          }
        }
      },
      "direnv": {
        "version": "2.28.0",
        "bottle": {
          "rebuild": 0,
          "cellar": ":any_skip_relocation",
          "prefix": "/usr/local",
          "root_url": "https://homebrew.bintray.com/bottles",
          "files": {
            "arm64_big_sur": {
              "url": "https://homebrew.bintray.com/bottles/direnv-2.28.0.arm64_big_sur.bottle.tar.gz",
              "sha256": "8fabe33920273c377ace461d6f2ff02a78569b230b7625402086ea4ebeffff38"
            },
            "big_sur": {
              "url": "https://homebrew.bintray.com/bottles/direnv-2.28.0.big_sur.bottle.tar.gz",
              "sha256": "64680c7245384e3cd59c4e0b9a1f32e5f0a26f5591b77c3736ed9160191571c3"
            },
            "catalina": {
              "url": "https://homebrew.bintray.com/bottles/direnv-2.28.0.catalina.bottle.tar.gz",
              "sha256": "c10f6a3b721b2c5c12b8bb3604bba9af3946edcada447327afa074b6c39e6996"
            },
            "mojave": {
              "url": "https://homebrew.bintray.com/bottles/direnv-2.28.0.mojave.bottle.tar.gz",
              "sha256": "8f1a615929f583478efb0c6853754dba806f94d95ed67c43f36062d95e50c636"
            }
          }
        }
      },
      "fish": {
        "version": "3.2.2",
        "bottle": {
          "rebuild": 0,
          "cellar": ":any",
          "prefix": "/usr/local",
          "root_url": "https://homebrew.bintray.com/bottles",
          "files": {
            "arm64_big_sur": {
              "url": "https://homebrew.bintray.com/bottles/fish-3.2.2.arm64_big_sur.bottle.tar.gz",
              "sha256": "f5c944adf3c809bb40601157c0879e7c1425e515d1eb94b262c8e2df58d91855"
            },
            "big_sur": {
              "url": "https://homebrew.bintray.com/bottles/fish-3.2.2.big_sur.bottle.tar.gz",
              "sha256": "3b580443ffe91b87d60d7bb5a85493a138fe6d731ac883f0769d6b06e1cb9a76"
            },
            "catalina": {
              "url": "https://homebrew.bintray.com/bottles/fish-3.2.2.catalina.bottle.tar.gz",
              "sha256": "150c9da4f2786cee5a8da6e5988b14f42213b2d3f051038f223c4986253d6d61"
            },
            "mojave": {
              "url": "https://homebrew.bintray.com/bottles/fish-3.2.2.mojave.bottle.tar.gz",
              "sha256": "04a1913039b23d096c7ed2481fdfb55f0cf16cb69761aaf85eff65095a1bdf7d"
            }
          }
        }
      },
      "zsh": {
        "version": "5.8_1",
        "bottle": {
          "rebuild": 0,
          "cellar": "/usr/local/Cellar",
          "prefix": "/usr/local",
          "root_url": "https://homebrew.bintray.com/bottles",
          "files": {
            "arm64_big_sur": {
              "url": "https://homebrew.bintray.com/bottles/zsh-5.8_1.arm64_big_sur.bottle.tar.gz",
              "sha256": "01ae59e3ea21dd7691120aec89552e4f4c10c6489a24b9cc23256129e3cbe7b6"
            },
            "big_sur": {
              "url": "https://homebrew.bintray.com/bottles/zsh-5.8_1.big_sur.bottle.tar.gz",
              "sha256": "a93717bcbb1a41829ac7549f7dea0e2be4bb11985be734f03801150338d6b8e6"
            },
            "catalina": {
              "url": "https://homebrew.bintray.com/bottles/zsh-5.8_1.catalina.bottle.tar.gz",
              "sha256": "aaf19f69f79ac2ef80ff31d3b2f0017f400bf40022f8626d5ae046990961a5f5"
            },
            "mojave": {
              "url": "https://homebrew.bintray.com/bottles/zsh-5.8_1.mojave.bottle.tar.gz",
              "sha256": "a40a54e4b686eb75f04e7dcc57391245a4f6b08a39825f7f6ebc9f76ebcbff46"
            },
            "high_sierra": {
              "url": "https://homebrew.bintray.com/bottles/zsh-5.8_1.high_sierra.bottle.tar.gz",
              "sha256": "edfbc09a9571fadf351e0f94e545a88aa33763518a3330c0bae497a6a259d63f"
            }
          }
        }
      },
      "wget": {
        "version": "1.21.1",
        "bottle": {
          "rebuild": 0,
          "cellar": "/usr/local/Cellar",
          "prefix": "/usr/local",
          "root_url": "https://homebrew.bintray.com/bottles",
          "files": {
            "arm64_big_sur": {
              "url": "https://homebrew.bintray.com/bottles/wget-1.21.1.arm64_big_sur.bottle.tar.gz",
              "sha256": "e9034fc9062d5d28972135be031876672aff18fa945ce37e9c2ee1e2c4287f3a"
            },
            "big_sur": {
              "url": "https://homebrew.bintray.com/bottles/wget-1.21.1.big_sur.bottle.tar.gz",
              "sha256": "e6ea2a50b8196206f7072360e713535bb16fb786c8b5fe23cab05757e0f67b13"
            },
            "catalina": {
              "url": "https://homebrew.bintray.com/bottles/wget-1.21.1.catalina.bottle.tar.gz",
              "sha256": "88116cb28d6b85e441d1bb9df0a1454b84f8b9d0e8817a5bee0f228acc59e75a"
            },
            "mojave": {
              "url": "https://homebrew.bintray.com/bottles/wget-1.21.1.mojave.bottle.tar.gz",
              "sha256": "ae4e6f1dc4ecaf2bbed7700e8d64cdc671bf9d6c085ba335f119861fd15956fe"
            }
          }
        }
      },
      "kubernetes-cli": {
        "version": "1.21.0",
        "bottle": {
          "rebuild": 0,
          "cellar": ":any_skip_relocation",
          "prefix": "/usr/local",
          "root_url": "https://homebrew.bintray.com/bottles",
          "files": {
            "arm64_big_sur": {
              "url": "https://homebrew.bintray.com/bottles/kubernetes-cli-1.21.0.arm64_big_sur.bottle.tar.gz",
              "sha256": "b9738e0e124ed9f41246b226f7b35d3ff1690cf490cb0de60df3832fba6033b9"
            },
            "big_sur": {
              "url": "https://homebrew.bintray.com/bottles/kubernetes-cli-1.21.0.big_sur.bottle.tar.gz",
              "sha256": "9af94c3f27d4a8d95fa874453c30208f8fff41becb19668260099dcd2708ec61"
            },
            "catalina": {
              "url": "https://homebrew.bintray.com/bottles/kubernetes-cli-1.21.0.catalina.bottle.tar.gz",
              "sha256": "d124e2ae0aa980f93648f325715ab88b09a9df9213f6a448e816630403271896"
            },
            "mojave": {
              "url": "https://homebrew.bintray.com/bottles/kubernetes-cli-1.21.0.mojave.bottle.tar.gz",
              "sha256": "6286ea1e71812947b61921a11c186f9d68aeb2fac012f8334d404cb97c71acc0"
            }
          }
        }
      },
      "libssh2": {
        "version": "1.9.0_1",
        "bottle": {
          "rebuild": 0,
          "cellar": ":any",
          "prefix": "/usr/local",
          "root_url": "https://homebrew.bintray.com/bottles",
          "files": {
            "arm64_big_sur": {
              "url": "https://homebrew.bintray.com/bottles/libssh2-1.9.0_1.arm64_big_sur.bottle.tar.gz",
              "sha256": "2840147f112db1ef9e353e104e8aff64fc6572a9194b3ded9cc006deaa46560c"
            },
            "big_sur": {
              "url": "https://homebrew.bintray.com/bottles/libssh2-1.9.0_1.big_sur.bottle.tar.gz",
              "sha256": "f9a31faed068d80fff508f2a08d1c8b7213a626d9c38dde22db9a8173a85c6ee"
            },
            "catalina": {
              "url": "https://homebrew.bintray.com/bottles/libssh2-1.9.0_1.catalina.bottle.tar.gz",
              "sha256": "2c4dcf8149663f9a133deac5bc42ce308d1ced90227cac391ca30b0ab2d381f9"
            },
            "mojave": {
              "url": "https://homebrew.bintray.com/bottles/libssh2-1.9.0_1.mojave.bottle.tar.gz",
              "sha256": "327c56ad6a54894e5ef9aa3019d2444d32f1d0fba80925940100e517dd3109c9"
            },
            "high_sierra": {
              "url": "https://homebrew.bintray.com/bottles/libssh2-1.9.0_1.high_sierra.bottle.tar.gz",
              "sha256": "ee29f44ef6fb59242fc7ee1747f02df2287722af4a45319289c9ee224367ba06"
            },
            "sierra": {
              "url": "https://homebrew.bintray.com/bottles/libssh2-1.9.0_1.sierra.bottle.tar.gz",
              "sha256": "769fbbdc4e67b8de15c269f66a6efe86c5b0195df56e7e46b44377a572800efa"
            }
          }
        }
      },
      "rbenv": {
        "version": "1.1.2",
        "bottle": {
          "rebuild": 0,
          "cellar": ":any",
          "prefix": "/usr/local",
          "root_url": "https://homebrew.bintray.com/bottles",
          "files": {
            "arm64_big_sur": {
              "url": "https://homebrew.bintray.com/bottles/rbenv-1.1.2.arm64_big_sur.bottle.tar.gz",
              "sha256": "19d0b9e3b11bcacdf692e78248c1b5764f7d3f4b58f2b83ad7b39562863ba82e"
            },
            "big_sur": {
              "url": "https://homebrew.bintray.com/bottles/rbenv-1.1.2.big_sur.bottle.tar.gz",
              "sha256": "60b045c8843745c45d01616ee3f71b91f6a16ee09c47e23a7817a3edabeaccfd"
            },
            "catalina": {
              "url": "https://homebrew.bintray.com/bottles/rbenv-1.1.2.catalina.bottle.tar.gz",
              "sha256": "503ed6d818502f00f031b9f49461934e252b9bfba2876e90a326fc27bb1052d6"
            },
            "mojave": {
              "url": "https://homebrew.bintray.com/bottles/rbenv-1.1.2.mojave.bottle.tar.gz",
              "sha256": "d1019098dee8d037587069398e5ad04e6d736f834dc44ae73943bec46b10b260"
            },
            "high_sierra": {
              "url": "https://homebrew.bintray.com/bottles/rbenv-1.1.2.high_sierra.bottle.tar.gz",
              "sha256": "b5984102794a9d39388ca1f6ec77965aeea29b971cc00cb5af8ede8ee6c926d6"
            },
            "sierra": {
              "url": "https://homebrew.bintray.com/bottles/rbenv-1.1.2.sierra.bottle.tar.gz",
              "sha256": "873175a851e5aa4f5b3438072030b945c252f08a9a07760c64dc045e2cce4724"
            }
          }
        }
      },
      "telnet": {
        "version": "63",
        "bottle": {
          "rebuild": 0,
          "cellar": ":any_skip_relocation",
          "prefix": "/usr/local",
          "root_url": "https://homebrew.bintray.com/bottles",
          "files": {
            "arm64_big_sur": {
              "url": "https://homebrew.bintray.com/bottles/telnet-63.arm64_big_sur.bottle.tar.gz",
              "sha256": "563fcbef08590e48a07079f00877e14f22f54849db11ee02ba7c935499a7ccd1"
            },
            "big_sur": {
              "url": "https://homebrew.bintray.com/bottles/telnet-63.big_sur.bottle.tar.gz",
              "sha256": "e6fb7de53e703755a72e227752f81023c2935567d935af638959e986da910b3e"
            },
            "catalina": {
              "url": "https://homebrew.bintray.com/bottles/telnet-63.catalina.bottle.tar.gz",
              "sha256": "7435a9fd2515158762a85197a4ad7141e430383e185e002da169dbbb638c952f"
            },
            "mojave": {
              "url": "https://homebrew.bintray.com/bottles/telnet-63.mojave.bottle.tar.gz",
              "sha256": "d5009f496dc6cf0c13b936996f98b91b0f12733ea9462843b56a39fc53b20fe0"
            },
            "high_sierra": {
              "url": "https://homebrew.bintray.com/bottles/telnet-63.high_sierra.bottle.tar.gz",
              "sha256": "af38f3c6dd4ff5eda2248671958e66595b39e74cdeecca52af4efb495bc659a7"
            }
          }
        }
      },
      "vim": {
        "version": "8.2.2725_1",
        "bottle": {
          "rebuild": 0,
          "cellar": "/usr/local/Cellar",
          "prefix": "/usr/local",
          "root_url": "https://homebrew.bintray.com/bottles",
          "files": {
            "arm64_big_sur": {
              "url": "https://homebrew.bintray.com/bottles/vim-8.2.2725_1.arm64_big_sur.bottle.tar.gz",
              "sha256": "ad0f72aa627d2c919482fd0ca8e9da68b54e61d3ffc07d0b553b72649d643d0c"
            },
            "big_sur": {
              "url": "https://homebrew.bintray.com/bottles/vim-8.2.2725_1.big_sur.bottle.tar.gz",
              "sha256": "c60b5c2a291944db1eef8ae7b7560b40bd96f2622ee7e49af780315e6de6d72b"
            },
            "catalina": {
              "url": "https://homebrew.bintray.com/bottles/vim-8.2.2725_1.catalina.bottle.tar.gz",
              "sha256": "09495cfc92c99f521341f99aa5df7a93c8d0d102ecac615a4133740be51cb7ae"
            },
            "mojave": {
              "url": "https://homebrew.bintray.com/bottles/vim-8.2.2725_1.mojave.bottle.tar.gz",
              "sha256": "04851f5c6270b6934dbc13c4f0b9580ca13d0453bef18f2d8d7348272b1d3151"
            }
          }
        }
      },
      "openldap": {
        "version": "2.4.58",
        "bottle": {
          "rebuild": 0,
          "cellar": "/usr/local/Cellar",
          "prefix": "/usr/local",
          "root_url": "https://homebrew.bintray.com/bottles",
          "files": {
            "arm64_big_sur": {
              "url": "https://homebrew.bintray.com/bottles/openldap-2.4.58.arm64_big_sur.bottle.tar.gz",
              "sha256": "978f2896e8daf4c88521af38226decc28f066c4205d1298b8048bf0c034c6061"
            },
            "big_sur": {
              "url": "https://homebrew.bintray.com/bottles/openldap-2.4.58.big_sur.bottle.tar.gz",
              "sha256": "a80cfbc1ab79fd40e646d0160ce4335f01fe41b13c0921e824af05ce3a656c3c"
            },
            "catalina": {
              "url": "https://homebrew.bintray.com/bottles/openldap-2.4.58.catalina.bottle.tar.gz",
              "sha256": "12b35571227819700575901d20a25cbcf605ba9ffbf89e8034223da045ff4706"
            },
            "mojave": {
              "url": "https://homebrew.bintray.com/bottles/openldap-2.4.58.mojave.bottle.tar.gz",
              "sha256": "3b93e3df9bd07b336e68f8a8a2ac80c07d305af3860a03733a95d84065b4770a"
            }
          }
        }
      },
      "zlib": {
        "version": "1.2.11",
        "bottle": {
          "rebuild": 0,
          "cellar": ":any",
          "prefix": "/usr/local",
          "root_url": "https://homebrew.bintray.com/bottles",
          "files": {
            "arm64_big_sur": {
              "url": "https://homebrew.bintray.com/bottles/zlib-1.2.11.arm64_big_sur.bottle.tar.gz",
              "sha256": "b480ed6baf10880f61b5a3097fb0921d44466857e1dde53a09e2ae4e378b1a8c"
            },
            "big_sur": {
              "url": "https://homebrew.bintray.com/bottles/zlib-1.2.11.big_sur.bottle.tar.gz",
              "sha256": "b95aa332dfc7c6dfb5e86fd30068f78e2cf87ee0232e5bef0adddae8215f543d"
            },
            "catalina": {
              "url": "https://homebrew.bintray.com/bottles/zlib-1.2.11.catalina.bottle.tar.gz",
              "sha256": "8ec66cf6faa310712767efc3022fdd16568a79234439f64bf579acb628f893bc"
            },
            "mojave": {
              "url": "https://homebrew.bintray.com/bottles/zlib-1.2.11.mojave.bottle.tar.gz",
              "sha256": "245a43a59c57f83848e7382974bb80a46eac1d53bcaefb1bdebd1f85107d4169"
            },
            "high_sierra": {
              "url": "https://homebrew.bintray.com/bottles/zlib-1.2.11.high_sierra.bottle.tar.gz",
              "sha256": "30548658b43cf66979f2756680fbb32d3c19c967e478ceea22d07f536b22bbce"
            },
            "sierra": {
              "url": "https://homebrew.bintray.com/bottles/zlib-1.2.11.sierra.bottle.tar.gz",
              "sha256": "f822b4dbab4a15b889316b89248c7b4d15d6af9dc460bf209b9425b0accb7fa3"
            },
            "el_capitan": {
              "url": "https://homebrew.bintray.com/bottles/zlib-1.2.11.el_capitan.bottle.tar.gz",
              "sha256": "3f912f6f1ce6c586128ebde29756c883b89409e652ca7aa9a29a773c2d4d0915"
            },
            "yosemite": {
              "url": "https://homebrew.bintray.com/bottles/zlib-1.2.11.yosemite.bottle.tar.gz",
              "sha256": "5b969eb38b90a3e31869586df9d62e59d359212b16c6a270aee690dd67caa491"
            }
          }
        }
      },
      "readline": {
        "version": "8.1",
        "bottle": {
          "rebuild": 0,
          "cellar": ":any",
          "prefix": "/usr/local",
          "root_url": "https://homebrew.bintray.com/bottles",
          "files": {
            "arm64_big_sur": {
              "url": "https://homebrew.bintray.com/bottles/readline-8.1.arm64_big_sur.bottle.tar.gz",
              "sha256": "940e7c2b80ef7f59b26726a5669a31fcb8ba7cbbb17eb1f2ca589dafa6e68e5e"
            },
            "big_sur": {
              "url": "https://homebrew.bintray.com/bottles/readline-8.1.big_sur.bottle.tar.gz",
              "sha256": "2cc3a9582e3c7e21eb3c2c8964abd33e9720fb4a9588c626d8424ff8cc9b1aed"
            },
            "catalina": {
              "url": "https://homebrew.bintray.com/bottles/readline-8.1.catalina.bottle.tar.gz",
              "sha256": "fe4de019cf549376a7743dcb0c86db8a08ca2b6d0dd2f8cb796dd7cf973dc2e9"
            },
            "mojave": {
              "url": "https://homebrew.bintray.com/bottles/readline-8.1.mojave.bottle.tar.gz",
              "sha256": "1ea5a8050482911b319dc3e1436ee03310ba79d75d855d40114ba6067e01b9c5"
            }
          }
        }
      },
      "sqlite3": {
        "version": "3.35.4",
        "bottle": {
          "rebuild": 0,
          "cellar": ":any",
          "prefix": "/usr/local",
          "root_url": "https://homebrew.bintray.com/bottles",
          "files": {
            "arm64_big_sur": {
              "url": "https://homebrew.bintray.com/bottles/sqlite-3.35.4.arm64_big_sur.bottle.tar.gz",
              "sha256": "ecb945b9df98160dd9c935fc128e862fbc7d4593ff5088916fc01f20ebd8f592"
            },
            "big_sur": {
              "url": "https://homebrew.bintray.com/bottles/sqlite-3.35.4.big_sur.bottle.tar.gz",
              "sha256": "861dc044ea531c39a2105010107feb95cf10977c3da94a4c4fce6aa1b3041c34"
            },
            "catalina": {
              "url": "https://homebrew.bintray.com/bottles/sqlite-3.35.4.catalina.bottle.tar.gz",
              "sha256": "a1aee82c8dec9baf0073f52d89ecc2ec3003a49afaa4180315ebf533e08a152b"
            },
            "mojave": {
              "url": "https://homebrew.bintray.com/bottles/sqlite-3.35.4.mojave.bottle.tar.gz",
              "sha256": "a1f00de2cbdf2b0f7749e54abfb2117fc0d9d48ead5d71c472994fbe7b29c3e2"
            }
          }
        }
      },
      "openssl": {
        "version": "1.1.1k",
        "bottle": {
          "rebuild": 0,
          "cellar": "/usr/local/Cellar",
          "prefix": "/usr/local",
          "root_url": "https://homebrew.bintray.com/bottles",
          "files": {
            "arm64_big_sur": {
              "url": "https://homebrew.bintray.com/bottles/openssl%401.1-1.1.1k.arm64_big_sur.bottle.tar.gz",
              "sha256": "0a75e0f116c0653bc7a2b422e5dc500e7e51557303aa4fca9c1a28786189c1da"
            },
            "big_sur": {
              "url": "https://homebrew.bintray.com/bottles/openssl%401.1-1.1.1k.big_sur.bottle.tar.gz",
              "sha256": "17d94c51ddfa8364baed5f3a754063e1ca75f807194f68d0b976619cf4e69c1a"
            },
            "catalina": {
              "url": "https://homebrew.bintray.com/bottles/openssl%401.1-1.1.1k.catalina.bottle.tar.gz",
              "sha256": "cb610ecdda346011031b890d7b7c6e1942d7fc08cf083b74f148ec7ffed8c7e1"
            },
            "mojave": {
              "url": "https://homebrew.bintray.com/bottles/openssl%401.1-1.1.1k.mojave.bottle.tar.gz",
              "sha256": "7928c80c309c6ece50b1c0d968a1e54011088cc896d26aa511249978a246bd50"
            }
          }
        }
      },
      "xz": {
        "version": "5.2.5",
        "bottle": {
          "rebuild": 0,
          "cellar": ":any",
          "prefix": "/usr/local",
          "root_url": "https://homebrew.bintray.com/bottles",
          "files": {
            "arm64_big_sur": {
              "url": "https://homebrew.bintray.com/bottles/xz-5.2.5.arm64_big_sur.bottle.tar.gz",
              "sha256": "c84206005787304416ed81094bd3a0cdd2ae8eb62649db5a3a44fa14b276d09f"
            },
            "big_sur": {
              "url": "https://homebrew.bintray.com/bottles/xz-5.2.5.big_sur.bottle.tar.gz",
              "sha256": "4fbd4a9e3eb49c27e83bd125b0e76d386c0e12ae1139d4dc9e31841fb8880a35"
            },
            "catalina": {
              "url": "https://homebrew.bintray.com/bottles/xz-5.2.5.catalina.bottle.tar.gz",
              "sha256": "2dcc8e0121c934d1e34ffdb37fcd70f0f7b5c2f4755f2f7cbcf360e9e54cb43b"
            },
            "mojave": {
              "url": "https://homebrew.bintray.com/bottles/xz-5.2.5.mojave.bottle.tar.gz",
              "sha256": "44483961b5d2b535b0ece1936c9d40b4bc7d9c7281646cca0fb476291ab9d4dc"
            },
            "high_sierra": {
              "url": "https://homebrew.bintray.com/bottles/xz-5.2.5.high_sierra.bottle.tar.gz",
              "sha256": "1491b2b20c40c3cb0b990f520768d7e876e4ab4a7dc1da9994d0150da34ba5c6"
            }
          }
        }
      }
    },
    "cask": {
      "google-chrome": {
        "version": "89.0.4389.114",
        "options": {
          "full_name": "google-chrome"
        }
      },
      "firefox": {
        "version": "87.0",
        "options": {
          "full_name": "firefox"
        }
      },
      "alfred": {
        "version": "4.3.2,1221",
        "options": {
          "full_name": "alfred"
        }
      },
      "bartender": {
        "version": "4.0.44,40044",
        "options": {
          "full_name": "bartender"
        }
      },
      "box-sync": {
        "version": "4.0.8009",
        "options": {
          "full_name": "box-sync"
        }
      },
      "discord": {
        "version": "0.0.262",
        "options": {
          "full_name": "discord"
        }
      },
      "docker": {
        "version": "3.3.0,62916",
        "options": {
          "full_name": "docker"
        }
      },
      "dropbox": {
        "version": "119.4.1772",
        "options": {
          "full_name": "dropbox"
        }
      },
      "flux": {
        "version": "41.4",
        "options": {
          "full_name": "flux"
        }
      },
      "gns3": {
        "version": "2.2.20",
        "options": {
          "full_name": "gns3"
        }
      },
      "iterm2": {
        "version": "3.4.4",
        "options": {
          "full_name": "iterm2"
        }
      },
      "microsoft-remote-desktop": {
        "version": "10.5.2",
        "options": {
          "full_name": "microsoft-remote-desktop"
        }
      },
      "logitech-presentation": {
        "version": "1.62.2",
        "options": {
          "full_name": "logitech-presentation"
        }
      },
      "kindle": {
        "version": "1.30.59055",
        "options": {
          "full_name": "kindle"
        }
      },
      "paragon-ntfs": {
        "version": "15",
        "options": {
          "full_name": "paragon-ntfs"
        }
      },
      "onedrive": {
        "version": "21.030.0211.0002",
        "options": {
          "full_name": "onedrive"
        }
      },
      "path-finder": {
        "version": "10.0.3,2089",
        "options": {
          "full_name": "path-finder"
        }
      },
      "postman": {
        "version": "8.2.1",
        "options": {
          "full_name": "postman"
        }
      },
      "scroll-reverser": {
        "version": "1.8,10433",
        "options": {
          "full_name": "scroll-reverser"
        }
      },
      "signal": {
        "version": "1.40.1",
        "options": {
          "full_name": "signal"
        }
      },
      "slack": {
        "version": "4.14.0",
        "options": {
          "full_name": "slack"
        }
      },
      "spotify": {
        "version": "1.1.56.595.g2d2da0de,1.1.56.595.g2d2da0de-24",
        "options": {
          "full_name": "spotify"
        }
      },
      "telegram-desktop": {
        "version": "2.7.1",
        "options": {
          "full_name": "telegram-desktop"
        }
      },
      "the-unarchiver": {
        "version": "4.2.4,131:1605625663",
        "options": {
          "full_name": "the-unarchiver"
        }
      },
      "protonmail-bridge": {
        "version": "1.6.9",
        "options": {
          "full_name": "protonmail-bridge"
        }
      },
      "visual-studio-code": {
        "version": "1.55.1",
        "options": {
          "full_name": "visual-studio-code"
        }
      },
      "virtualbox": {
        "version": "6.1.18,142142",
        "options": {
          "full_name": "virtualbox"
        }
      },
      "vagrant": {
        "version": "2.2.15",
        "options": {
          "full_name": "vagrant"
        }
      },
      "vlc": {
        "version": "3.0.12",
        "options": {
          "full_name": "vlc"
        }
      },
      "vnc-viewer": {
        "version": "6.21.118",
        "options": {
          "full_name": "vnc-viewer"
        }
      },
      "wireshark": {
        "version": "3.4.4",
        "options": {
          "full_name": "wireshark"
        }
      },
      "zoom": {
        "version": "5.6.1.560",
        "options": {
          "full_name": "zoom"
        }
      }
    }
  },
  "system": {
    "macos": {
      "big_sur": {
        "HOMEBREW_VERSION": "3.0.11",
        "HOMEBREW_PREFIX": "/usr/local",
        "Homebrew/homebrew-core": "5100b1bd14345a1006e44d0e23dcd939e8517775",
        "CLT": "12.4.0.0.1.1610135815",
        "Xcode": "12.0",
        "macOS": "11.2.3"
      }
    }
  }
}
